json_delta/__init__.py
json_delta/_diff.py
json_delta/_patch.py
json_delta/_udiff.py
json_delta/_upatch.py
json_delta/_util.py
json_delta-2.0.1.data/scripts/json_cat
json_delta-2.0.1.data/scripts/json_diff
json_delta-2.0.1.data/scripts/json_patch
json_delta-2.0.1.dist-info/LICENSE
json_delta-2.0.1.dist-info/METADATA
json_delta-2.0.1.dist-info/WHEEL
json_delta-2.0.1.dist-info/top_level.txt
json_delta-2.0.1.dist-info/zip-safe
json_delta-2.0.1.dist-info/RECORD
