Metadata-Version: 2.1
Name: json-delta
Version: 2.0.1
Summary: A diff/patch pair for JSON-serialized data structures.
Home-page: http://json-delta.readthedocs.org/
Author: Phil Roberts
Author-email: himself@phil-roberts.name
License: BSD
Keywords: JSON,delta,diff,patch,compression
Platform: UNKNOWN
Classifier: Development Status :: 4 - Beta
Classifier: Intended Audience :: Developers
Classifier: License :: OSI Approved :: BSD License
Classifier: Programming Language :: Python :: 2
Classifier: Programming Language :: Python :: 2.7
Classifier: Programming Language :: Python :: 3
Classifier: Programming Language :: Python :: 3.2
Classifier: Programming Language :: Python :: 3.3
Classifier: Programming Language :: Python :: 3.4
